README.rst
setup.py
pypgen.egg-info/PKG-INFO
pypgen.egg-info/SOURCES.txt
pypgen.egg-info/dependency_links.txt
pypgen.egg-info/requires.txt
pypgen.egg-info/top_level.txt
pypgen/fstats/__init__.py
pypgen/fstats/fstats.py
pypgen/misc/__init__.py
pypgen/misc/helpers.py
pypgen/parser/VCF.py
pypgen/parser/__init__.py
scripts/vcf2Dadi.py
scripts/vcf2phylip.py
scripts/vcf_sliding_window.py
scripts/vcf_snpwise_fstats.py