Metadata-Version: 1.0
Name: pypgen
Version: 0.2.0
Summary: Genetic diversity metrics from popoulation genomic datasets.
Home-page: http://pypi.python.org/pypi/pypgen/
Author: Nicholas G. Crawford
Author-email: ngcrawford@gmail.com
License: LICENSE.txt
Platform: UNKNOWN
